{
 "bendStrength": 20.0, 
 "collide": true, 
 "dropoff": 1.0, 
 "isDynamic": true, 
 "strengthDropoff.strengthDropoff_Interp": null, 
 "bendBreakAngle": 360.0, 
 "binMembership": null, 
 "customTreatment": null, 
 "identification": 0, 
 "connectWithinComponent": false,
 "maxIterations": 5000, 
 "friction": 0.0, 
 "connectionDensityRange.connectionDensityRange_FloatValue": null, 
 "strengthDropoff": null, 
 "creator": null,
 "collideWidthScale": 1.0, 
 "overridePlayback": true,
 "connectionMethod": 0, 
 "template": false, 
 "containerType": null,
 "dropoffDistance": 50.0, 
 "strengthDropoff.strengthDropoff_FloatValue": null, 
 "instObjGroups.objectGroups.objectGrpCompList": null, 
 "viewName": null, 
 "strengthDropoff.strengthDropoff_Position": null, 
 "restLengthScale": 1.0, 
 "connectionUpdate": 0, 
 "rmbCommand": null, 
 "evalStart": null, 
 "maxDistance": 0.1,
 "evalCurrent": null, 
 "ghostRangeStart": 0.0, 
 "borderConnections": null, 
 "constraintMethod": 1,
 "singleSided": true, 
 "iterations": 20, 
 "overrideLevelOfDetail": 0, 
 "force": 0.0, 
 "ghosting": false, 
 "isHistoricallyInteresting": 2, 
 "damp": 0.0, 
 "glueStrengthScale": 1.0, 
 "tangentStrength": 10.0, 
 "boundingBoxCenterZ": 0.0, 
 "drawOverride": null, 
 "enable": true, 
 "instObjGroups.objectGroups.objectGroupId": null, 
 "restLengthMethod": 0, 
 "visibility": true, 
 "glueStrength": 1.0, 
 "motionDrag": 0.0, 
 "connectionDensityRange": null, 
 "frozen": false, 
 "minIterations": 0, 
 "localCollide": false, 
 "excludeCollisions": false, 
 "restLength": 0.0, 
 "bend": false, 
 "isCollapsed": false, 
 "displayConnections": true, 
 "blackBox": false, 
 "templateName": null, 
 "ghostingControl": 0, 
 "connectionDensityRange.connectionDensityRange_Position": null, 
 "nodeState": 0, 
 "publishedNodeInfo.isHierarchicalNode": null, 
 "connectionDensityRange.connectionDensityRange_Interp": null, 
 "connectionDensity": 1.0, 
 "hiddenInOutliner": false, 
 "hyperLayout": null, 
 "layerRenderable": true, 
 "strength": 20.0,
 "componentIds": null, 
 "componentRelation": 0, 
 "constraintRelation": 0, 
 "viewMode": 2, 
 "caching": false, 
}